django_actual/__init__.py
django_actual/admin.py
django_actual/auth_backends.py
django_actual/classmaker.py
django_actual/compat.py
django_actual/context_processors.py
django_actual/db_fields.py
django_actual/decorators.py
django_actual/email_backends.py
django_actual/helper.py
django_actual/http.py
django_actual/middleware.py
django_actual/mixin.py
django_actual/scaffold.py
django_actual/session.py
django_actual/settings.py
django_actual/tests.py
django_actual/tzinfo.py
django_actual/management/__init__.py
django_actual/management/commands/__init__.py
django_actual/management/commands/generate_secret_key.py
django_actual/management/commands/scaffold.py
django_actual/static/django_actual/js/ajax_form.js
django_actual/static/django_actual/js/common.js
django_actual/templates/common/admin/nested.html
django_actual/templates/common/admin/nested_tabular.html
django_actual/templates/common/fragments/checkbox_field.html
django_actual/templates/common/fragments/form_field.html
django_actual/templates/common/fragments/multi_checkbox_field.html
django_actual/templates/common/fragments/radio_field.html
django_actual/templatetags/__init__.py
django_actual/templatetags/custom_tags.py
django_actual_helpers-0.9.2.0b12.dist-info/AUTHORS
django_actual_helpers-0.9.2.0b12.dist-info/LICENSE
django_actual_helpers-0.9.2.0b12.dist-info/METADATA
django_actual_helpers-0.9.2.0b12.dist-info/WHEEL
django_actual_helpers-0.9.2.0b12.dist-info/top_level.txt
django_actual_helpers-0.9.2.0b12.dist-info/RECORD
