Metadata-Version: 2.1
Name: django-actual-helpers
Version: 0.9.2.0b12
Summary: Common things every Django app needs Based on django-common-helpers package
Home-page: http://github.com/sipmann/django-actual-helpers
Author: Sipmann
Author-email: mauricio@sipmann.com
License: UNKNOWN
Keywords: django,scaffold
Platform: UNKNOWN
Classifier: Framework :: Django
Classifier: Development Status :: 4 - Beta
Classifier: Programming Language :: Python :: 3
Classifier: Intended Audience :: Developers
Classifier: Intended Audience :: System Administrators
Classifier: Operating System :: OS Independent
Classifier: Topic :: Software Development
Requires-Python: >=3
Requires-Dist: Django (>=3.1.4)
